Week5/w5:FSM/counter.v
module counter(
    input clk,
    input rst,        
    input clear,       // New input: clears counter when high
    output reg [3:0] count_out  
);

    always @(posedge clk or posedge rst) begin
        if (rst || clear) 
            count_out <= 4'b0000;  // Reset count to 0
        else 
            count_out <= count_out + 4'b0001;  
    end

endmodule

Week5/w5:FSM/traffic_light.v
module traffic_light_fsm (
    input clk,
    input reset,           // Asynchronous reset
    output reg [2:0] light // Traffic light output: 3'b001 (RED), 3'b010 (GREEN), 3'b100 (YELLOW)
);

    // State encoding
    parameter RED = 2'b00;
    parameter GREEN = 2'b01;
    parameter YELLOW = 2'b10;

    parameter THRESHOLD_RED = 10;    // Change this value as needed
    parameter THRESHOLD_GREEN = 10;
    parameter THRESHOLD_YELLOW = 5;
    reg [1:0] current_state, next_state;
    wire [3:0] count_out; // Wire to receive counter output


    // Instantiate counter module with `clear` signal
    counter counter_inst (
        .clk(clk),
        .rst(reset),
        .clear(current_state != next_state), // Clear counter when state changes
        .count_out(count_out)
    );


    // Model state register (sequential logic)
    always @(posedge clk or posedge reset) begin
        if (reset) begin
            current_state <= RED;
        end else begin
            current_state <= next_state;
        end
    end

    // Model next state decode logic (combinational logic)
    always @(*) begin
        case (current_state)
            RED: begin
                if (count_out>=THRESHOLD_RED) begin
                    next_state = GREEN;
                end else begin
                    next_state = RED;
                end
            end
            GREEN: begin
                if (count_out >=THRESHOLD_GREEN) begin
                    next_state = YELLOW;
                end else begin
                    next_state = GREEN;
                end
            end
            YELLOW: begin
                if (count_out >= THRESHOLD_YELLOW) begin
                    next_state = RED;
                end else begin
                    next_state = YELLOW;
                end
            end
            default: begin
                next_state = RED;
            end
        endcase
    end

    // Model output logic (combinational logic)
    always @(*) begin
        case (current_state)
            RED: begin
                light = 3'b001; // RED light
            end
            GREEN: begin
                light = 3'b010; // GREEN light
            end
            YELLOW: begin
                light = 3'b100; // YELLOW light
            end
            default: begin
                light = 3'b001; // Default to RED light
            end
        endcase
    end
endmodule

Week5/w5:FSM/traffic.vcd
$version Generated by VerilatedVcd $end
$timescale 1ps $end
 $scope module TOP $end
  $var wire 1 ' clk $end
  $var wire 1 ( reset $end
  $var wire 3 ) light [2:0] $end
  $scope module traffic_light_fsm $end
   $var wire 1 ' clk $end
   $var wire 1 ( reset $end
   $var wire 3 ) light [2:0] $end
   $var wire 2 * RED [1:0] $end
   $var wire 2 + GREEN [1:0] $end
   $var wire 2 , YELLOW [1:0] $end
   $var wire 32 - THRESHOLD_RED [31:0] $end
   $var wire 32 - THRESHOLD_GREEN [31:0] $end
   $var wire 32 . THRESHOLD_YELLOW [31:0] $end
   $var wire 2 # current_state [1:0] $end
   $var wire 2 $ next_state [1:0] $end
   $var wire 4 % count_out [3:0] $end
   $scope module counter_inst $end
    $var wire 1 ' clk $end
    $var wire 1 ( rst $end
    $var wire 1 & clear $end
    $var wire 4 % count_out [3:0] $end
   $upscope $end
  $upscope $end
 $upscope $end
$enddefinitions $end


#0
b00 #
b00 $
b0000 %
0&
0'
1(
b001 )
b00 *
b01 +
b10 ,
b00000000000000000000000000001010 -
b00000000000000000000000000000101 .
#1
1'
#2
0'
#3
1'
#4
0'
#5
b0001 %
1'
0(
#6
0'
#7
b0010 %
1'
#8
0'
#9
b0011 %
1'
#10
0'
#11
b0100 %
1'
#12
0'
#13
b0101 %
1'
#14
0'
#15
b0110 %
1'
#16
0'
#17
b0111 %
1'
#18
0'
#19
b1000 %
1'
#20
0'
#21
b1001 %
1'
#22
0'
#23
b01 $
b1010 %
1&
1'
#24
0'
#25
b01 #
b0000 %
0&
1'
b010 )
#26
0'
#27
b0001 %
1'
#28
0'
#29
b0010 %
1'
#30
0'
#31
b0011 %
1'
#32
0'
#33
b0100 %
1'
#34
0'
#35
b0101 %
1'
#36
0'
#37
b0110 %
1'
#38
0'
#39
b0111 %
1'
#40
0'
#41
b1000 %
1'
#42
0'
#43
b1001 %
1'
#44
0'
#45
b10 $
b1010 %
1&
1'
#46
0'
#47
b10 #
b0000 %
0&
1'
b100 )
#48
0'
#49
b0001 %
1'
#50
0'
#51
b0010 %
1'
#52
0'
#53
b0011 %
1'
#54
0'
#55
b0100 %
1'
#56
0'
#57
b00 $
b0101 %
1&
1'
#58
0'
#59
b00 #
b0000 %
0&
1'
b001 )
#60
0'
#61
b0001 %
1'
#62
0'
#63
b0010 %
1'
#64
0'
#65
b0011 %
1'
#66
0'
#67
b0100 %
1'
#68
0'
#69
b0101 %
1'
#70
0'
#71
b0110 %
1'
#72
0'
#73
b0111 %
1'
#74
0'
#75
b1000 %
1'
#76
0'
#77
b1001 %
1'
#78
0'
#79
b01 $
b1010 %
1&
1'
#80
0'
#81
b01 #
b0000 %
0&
1'
b010 )
#82
0'
#83
b0001 %
1'
#84
0'
#85
b0010 %
1'
#86
0'
#87
b0011 %
1'
#88
0'
#89
b0100 %
1'
#90
0'
#91
b0101 %
1'
#92
0'
#93
b0110 %
1'
#94
0'
#95
b0111 %
1'
#96
0'
#97
b1000 %
1'
#98
0'
#99
b1001 %
1'
#100
0'
#101
b10 $
b1010 %
1&
1'
#102
0'
#103
b10 #
b0000 %
0&
1'
b100 )
