Week4/w4:FibonacciGenerator/fibonacci_generator.v
module fibonacci_generator (
    input clk,        // Clock signal
    input rst,        // Synchronous reset
    input enable,     // Enable signal for calculating next Fibonacci number
    output reg [31:0] fib_out  // Output for the current Fibonacci number
);

reg [31:0] fib_prev1;  // F(n-1)
reg [31:0] fib_prev2;  // F(n-2)

always @(posedge clk or posedge rst) begin
    if (rst) begin
        // Initialize Fibonacci numbers
        fib_prev1 <= 32'd1;  // F(1) = 1
        fib_prev2 <= 32'd0;  // F(0) = 0
        fib_out <= 32'd0;    // Current Fibonacci number = F(0)
    end else if (enable) begin
        // Compute next Fibonacci number
        fib_out <= fib_prev1 + fib_prev2;
        
        // Update previous Fibonacci numbers
        fib_prev2 <= fib_prev1;
        fib_prev1 <= fib_prev1 + fib_prev2;
        
        
    end
end

endmodule

Week4/w4:FibonacciGenerator/fibonacci_generator.vcd
$version Generated by VerilatedVcd $end
$timescale 1ps $end
 $scope module TOP $end
  $var wire 1 # clk $end
  $var wire 1 $ rst $end
  $var wire 1 % enable $end
  $var wire 32 & fib_out [31:0] $end
  $scope module fibonacci_generator $end
   $var wire 1 # clk $end
   $var wire 1 $ rst $end
   $var wire 1 % enable $end
   $var wire 32 & fib_out [31:0] $end
   $var wire 32 ' fib_prev1 [31:0] $end
   $var wire 32 ( fib_prev2 [31:0] $end
  $upscope $end
 $upscope $end
$enddefinitions $end


#0
1#
1$
1%
b00000000000000000000000000000000 &
b00000000000000000000000000000000 '
b00000000000000000000000000000000 (
#1
0#
#2
1#
b00000000000000000000000000000001 '
#3
0#
#4
1#
#5
0#
#6
1#
#7
0#
#8
1#
#9
0#
#10
1#
0$
b00000000000000000000000000000001 &
b00000000000000000000000000000001 (
#11
0#
#12
1#
b00000000000000000000000000000010 &
b00000000000000000000000000000010 '
#13
0#
#14
1#
b00000000000000000000000000000011 &
b00000000000000000000000000000011 '
b00000000000000000000000000000010 (
#15
0#
#16
1#
b00000000000000000000000000000101 &
b00000000000000000000000000000101 '
b00000000000000000000000000000011 (
#17
0#
#18
1#
b00000000000000000000000000001000 &
b00000000000000000000000000001000 '
b00000000000000000000000000000101 (
#19
0#
#20
1#
b00000000000000000000000000001101 &
b00000000000000000000000000001101 '
b00000000000000000000000000001000 (
#21
0#
#22
1#
b00000000000000000000000000010101 &
b00000000000000000000000000010101 '
b00000000000000000000000000001101 (
#23
0#
#24
1#
b00000000000000000000000000100010 &
b00000000000000000000000000100010 '
b00000000000000000000000000010101 (
#25
0#
#26
1#
b00000000000000000000000000110111 &
b00000000000000000000000000110111 '
b00000000000000000000000000100010 (
#27
0#
#28
1#
b00000000000000000000000001011001 &
b00000000000000000000000001011001 '
b00000000000000000000000000110111 (
#29
0#
#30
1#
b00000000000000000000000010010000 &
b00000000000000000000000010010000 '
b00000000000000000000000001011001 (
#31
0#
#32
1#
b00000000000000000000000011101001 &
b00000000000000000000000011101001 '
b00000000000000000000000010010000 (
#33
0#
#34
1#
b00000000000000000000000101111001 &
b00000000000000000000000101111001 '
b00000000000000000000000011101001 (
#35
0#
#36
1#
b00000000000000000000001001100010 &
b00000000000000000000001001100010 '
b00000000000000000000000101111001 (
#37
0#
#38
1#
b00000000000000000000001111011011 &
b00000000000000000000001111011011 '
b00000000000000000000001001100010 (
#39
0#
#40
1#
b00000000000000000000011000111101 &
b00000000000000000000011000111101 '
b00000000000000000000001111011011 (
#41
0#
#42
1#
b00000000000000000000101000011000 &
b00000000000000000000101000011000 '
b00000000000000000000011000111101 (
#43
0#
#44
1#
b00000000000000000001000001010101 &
b00000000000000000001000001010101 '
b00000000000000000000101000011000 (
#45
0#
#46
1#
b00000000000000000001101001101101 &
b00000000000000000001101001101101 '
b00000000000000000001000001010101 (
#47
0#
#48
1#
b00000000000000000010101011000010 &
b00000000000000000010101011000010 '
b00000000000000000001101001101101 (
#49
0#
#50
1#
b00000000000000000100010100101111 &
b00000000000000000100010100101111 '
b00000000000000000010101011000010 (
#51
0#
#52
1#
b00000000000000000110111111110001 &
b00000000000000000110111111110001 '
b00000000000000000100010100101111 (
#53
0#
#54
1#
b00000000000000001011010100100000 &
b00000000000000001011010100100000 '
b00000000000000000110111111110001 (
#55
0#
#56
1#
b00000000000000010010010100010001 &
b00000000000000010010010100010001 '
b00000000000000001011010100100000 (
#57
0#
#58
1#
b00000000000000011101101000110001 &
b00000000000000011101101000110001 '
b00000000000000010010010100010001 (
#59
0#
#60
1#
b00000000000000101111111101000010 &
b00000000000000101111111101000010 '
b00000000000000011101101000110001 (
#61
0#
#62
1#
b00000000000001001101100101110011 &
b00000000000001001101100101110011 '
b00000000000000101111111101000010 (
#63
0#
#64
1#
b00000000000001111101100010110101 &
b00000000000001111101100010110101 '
b00000000000001001101100101110011 (
#65
0#
#66
1#
b00000000000011001011001000101000 &
b00000000000011001011001000101000 '
b00000000000001111101100010110101 (
#67
0#
#68
1#
b00000000000101001000101011011101 &
b00000000000101001000101011011101 '
b00000000000011001011001000101000 (
#69
0#
#70
1#
b00000000001000010011110100000101 &
b00000000001000010011110100000101 '
b00000000000101001000101011011101 (
#71
0#
#72
1#
b00000000001101011100011111100010 &
b00000000001101011100011111100010 '
b00000000001000010011110100000101 (
#73
0#
#74
1#
b00000000010101110000010011100111 &
b00000000010101110000010011100111 '
b00000000001101011100011111100010 (
#75
0#
#76
1#
b00000000100011001100110011001001 &
b00000000100011001100110011001001 '
b00000000010101110000010011100111 (
#77
0#
#78
1#
b00000000111000111101000110110000 &
b00000000111000111101000110110000 '
b00000000100011001100110011001001 (
#79
0#
#80
1#
b00000001011100001001111001111001 &
b00000001011100001001111001111001 '
b00000000111000111101000110110000 (
#81
0#
#82
1#
b00000010010101000111000000101001 &
b00000010010101000111000000101001 '
b00000001011100001001111001111001 (
#83
0#
#84
1#
b00000011110001010000111010100010 &
b00000011110001010000111010100010 '
b00000010010101000111000000101001 (
#85
0#
#86
1#
b00000110000110010111111011001011 &
b00000110000110010111111011001011 '
b00000011110001010000111010100010 (
#87
0#
#88
1#
b00001001110111101000110101101101 &
b00001001110111101000110101101101 '
b00000110000110010111111011001011 (
#89
0#
#90
1#
b00001111111110000000110000111000 &
b00001111111110000000110000111000 '
b00001001110111101000110101101101 (
#91
0#
#92
1#
b00011001110101101001100110100101 &
b00011001110101101001100110100101 '
b00001111111110000000110000111000 (
#93
0#
#94
1#
b00101001110011101010010111011101 &
b00101001110011101010010111011101 '
b00011001110101101001100110100101 (
#95
0#
#96
1#
b01000011101001010011111110000010 &
b01000011101001010011111110000010 '
b00101001110011101010010111011101 (
#97
0#
#98
1#
b01101101011100111110010101011111 &
b01101101011100111110010101011111 '
b01000011101001010011111110000010 (
#99
0#
#100
1#
b10110001000110010010010011100001 &
b10110001000110010010010011100001 '
b01101101011100111110010101011111 (
#101
0#
#102
1#
b00011110100011010000101001000000 &
b00011110100011010000101001000000 '
b10110001000110010010010011100001 (
#103
0#
#104
1#
b11001111101001100010111100100001 &
b11001111101001100010111100100001 '
b00011110100011010000101001000000 (
#105
0#
#106
1#
b11101110001100110011100101100001 &
b11101110001100110011100101100001 '
b11001111101001100010111100100001 (
#107
0#
#108
1#
b10111101110110010110100010000010 &
b10111101110110010110100010000010 '
b11101110001100110011100101100001 (
#109
0#
#110
1#
b10101100000011001010000111100011 &
b10101100000011001010000111100011 '
b10111101110110010110100010000010 (
#111
0#
#112
1#
b01101001111001100000101001100101 &
b01101001111001100000101001100101 '
b10101100000011001010000111100011 (
#113
0#
#114
1#
b00010101111100101010110001001000 &
b00010101111100101010110001001000 '
b01101001111001100000101001100101 (
#115
0#
#116
1#
b01111111110110001011011010101101 &
b01111111110110001011011010101101 '
b00010101111100101010110001001000 (
#117
0#
#118
1#
b10010101110010110110001011110101 &
b10010101110010110110001011110101 '
b01111111110110001011011010101101 (
#119
0#
#120
1#
b00010101101001000001100110100010 &
b00010101101001000001100110100010 '
b10010101110010110110001011110101 (
#121
0#
#122
1#
b10101011011011110111110010010111 &
b10101011011011110111110010010111 '
b00010101101001000001100110100010 (
#123
0#
#124
1#
b11000001000100111001011000111001 &
b11000001000100111001011000111001 '
b10101011011011110111110010010111 (
#125
0#
#126
1#
b01101100100000110001001011010000 &
b01101100100000110001001011010000 '
b11000001000100111001011000111001 (
#127
0#
#128
1#
b00101101100101101010100100001001 &
b00101101100101101010100100001001 '
b01101100100000110001001011010000 (
#129
0#
#130
1#
b10011010000110011011101111011001 &
b10011010000110011011101111011001 '
b00101101100101101010100100001001 (
#131
0#
#132
1#
b11000111101100000110010011100010 &
b11000111101100000110010011100010 '
b10011010000110011011101111011001 (
#133
0#
#134
1#
b01100001110010100010000010111011 &
b01100001110010100010000010111011 '
b11000111101100000110010011100010 (
#135
0#
#136
1#
b00101001011110101000010110011101 &
b00101001011110101000010110011101 '
b01100001110010100010000010111011 (
#137
0#
#138
1#
b10001011010001001010011001011000 &
b10001011010001001010011001011000 '
b00101001011110101000010110011101 (
#139
0#
#140
1#
b10110100101111110010101111110101 &
b10110100101111110010101111110101 '
b10001011010001001010011001011000 (
#141
0#
#142
1#
b01000000000000111101001001001101 &
b01000000000000111101001001001101 '
b10110100101111110010101111110101 (
#143
0#
#144
1#
b11110100110000101111111001000010 &
b11110100110000101111111001000010 '
b01000000000000111101001001001101 (
#145
0#
#146
1#
b00110100110001101101000010001111 &
b00110100110001101101000010001111 '
b11110100110000101111111001000010 (
#147
0#
#148
1#
b00101001100010011100111011010001 &
b00101001100010011100111011010001 '
b00110100110001101101000010001111 (
#149
0#
#150
1#
b01011110010100001001111101100000 &
b01011110010100001001111101100000 '
b00101001100010011100111011010001 (
#151
0#
#152
1#
b10000111110110100110111000110001 &
b10000111110110100110111000110001 '
b01011110010100001001111101100000 (
#153
0#
#154
1#
b11100110001010110000110110010001 &
b11100110001010110000110110010001 '
b10000111110110100110111000110001 (
#155
0#
#156
1#
b01101110000001010111101111000010 &
b01101110000001010111101111000010 '
b11100110001010110000110110010001 (
#157
0#
#158
1#
b01010100001100001000100101010011 &
b01010100001100001000100101010011 '
b01101110000001010111101111000010 (
#159
0#
#160
1#
b11000010001101100000010100010101 &
b11000010001101100000010100010101 '
b01010100001100001000100101010011 (
#161
0#
#162
1#
b00010110011001101000111001101000 &
b00010110011001101000111001101000 '
b11000010001101100000010100010101 (
#163
0#
#164
1#
b11011000100111001001001101111101 &
b11011000100111001001001101111101 '
b00010110011001101000111001101000 (
#165
0#
#166
1#
b11101111000000110010000111100101 &
b11101111000000110010000111100101 '
b11011000100111001001001101111101 (
#167
0#
#168
1#
b11000111100111111011010101100010 &
b11000111100111111011010101100010 '
b11101111000000110010000111100101 (
#169
0#
#170
1#
b10110110101000101101011101000111 &
b10110110101000101101011101000111 '
b11000111100111111011010101100010 (
#171
0#
#172
1#
b01111110010000101000110010101001 &
b01111110010000101000110010101001 '
b10110110101000101101011101000111 (
#173
0#
#174
1#
b00110100111001010110001111110000 &
b00110100111001010110001111110000 '
b01111110010000101000110010101001 (
#175
0#
#176
1#
b10110011001001111111000010011001 &
b10110011001001111111000010011001 '
b00110100111001010110001111110000 (
#177
0#
#178
1#
b11101000000011010101010010001001 &
b11101000000011010101010010001001 '
b10110011001001111111000010011001 (
#179
0#
#180
1#
b10011011001101010100010100100010 &
b10011011001101010100010100100010 '
b11101000000011010101010010001001 (
#181
0#
#182
1#
b10000011010000101001100110101011 &
b10000011010000101001100110101011 '
b10011011001101010100010100100010 (
#183
0#
#184
1#
b00011110011101111101111011001101 &
b00011110011101111101111011001101 '
b10000011010000101001100110101011 (
#185
0#
#186
1#
b10100001101110100111100001111000 &
b10100001101110100111100001111000 '
b00011110011101111101111011001101 (
#187
0#
#188
1#
b11000000001100100101011101000101 &
b11000000001100100101011101000101 '
b10100001101110100111100001111000 (
#189
0#
#190
1#
b01100001111011001100111110111101 &
b01100001111011001100111110111101 '
b11000000001100100101011101000101 (
#191
0#
#192
1#
b00100010000111110010011100000010 &
b00100010000111110010011100000010 '
b01100001111011001100111110111101 (
#193
0#
#194
1#
b10000100000010111111011010111111 &
b10000100000010111111011010111111 '
b00100010000111110010011100000010 (
#195
0#
#196
1#
b10100110001010110001110111000001 &
b10100110001010110001110111000001 '
b10000100000010111111011010111111 (
#197
0#
#198
1#
b00101010001101110001010010000000 &
b00101010001101110001010010000000 '
b10100110001010110001110111000001 (
#199
0#
#200
1#
b11010000011000100011001001000001 &
b11010000011000100011001001000001 '
b00101010001101110001010010000000 (
#201
0#
#202
1#
b11111010100110010100011011000001 &
b11111010100110010100011011000001 '
b11010000011000100011001001000001 (
#203
0#
#204
1#
b11001010111110110111100100000010 &
b11001010111110110111100100000010 '
b11111010100110010100011011000001 (
#205
0#
#206
1#
b11000101100101001011111111000011 &
b11000101100101001011111111000011 '
b11001010111110110111100100000010 (
#207
0#
#208
1#
b10010000100100000011100011000101 &
b10010000100100000011100011000101 '
b11000101100101001011111111000011 (
#209
0#
#210
1#
b01010110001001001111100010001000 &
b01010110001001001111100010001000 '
b10010000100100000011100011000101 (
#211
0#
#212
1#
b11100110101101010011000101001101 &
b11100110101101010011000101001101 '
b01010110001001001111100010001000 (
#213
0#
#214
1#
b00111100110110100010100111010101 &
b00111100110110100010100111010101 '
b11100110101101010011000101001101 (
#215
0#
#216
1#
b00100011100011110101101100100010 &
b00100011100011110101101100100010 '
b00111100110110100010100111010101 (
#217
0#
#218
1#
b01100000011010011000010011110111 &
b01100000011010011000010011110111 '
b00100011100011110101101100100010 (
#219
0#
#220
1#
b10000011111110001110000000011001 &
b10000011111110001110000000011001 '
b01100000011010011000010011110111 (
#221
0#
#222
1#
b11100100011000100110010100010000 &
b11100100011000100110010100010000 '
b10000011111110001110000000011001 (
#223
0#
#224
1#
b01101000010110110100010100101001 &
b01101000010110110100010100101001 '
b11100100011000100110010100010000 (
#225
0#
#226
1#
b01001100101111011010101000111001 &
b01001100101111011010101000111001 '
b01101000010110110100010100101001 (
#227
0#
#228
1#
b10110101000110001110111101100010 &
b10110101000110001110111101100010 '
b01001100101111011010101000111001 (
#229
0#
#230
1#
b00000001110101101001100110011011 &
b00000001110101101001100110011011 '
b10110101000110001110111101100010 (
#231
0#
#232
1#
b10110110111011111000100011111101 &
b10110110111011111000100011111101 '
b00000001110101101001100110011011 (
#233
0#
#234
1#
b10111000110001100010001010011000 &
b10111000110001100010001010011000 '
b10110110111011111000100011111101 (
#235
0#
#236
1#
b01101111101101011010101110010101 &
b01101111101101011010101110010101 '
b10111000110001100010001010011000 (
#237
0#
#238
1#
b00101000011110111100111000101101 &
b00101000011110111100111000101101 '
b01101111101101011010101110010101 (
#239
0#
#240
1#
b10011000001100010111100111000010 &
b10011000001100010111100111000010 '
b00101000011110111100111000101101 (
#241
0#
#242
1#
b11000000101011010100011111101111 &
b11000000101011010100011111101111 '
b10011000001100010111100111000010 (
#243
0#
#244
1#
b01011000110111101100000110110001 &
b01011000110111101100000110110001 '
b11000000101011010100011111101111 (
#245
0#
#246
1#
b00011001100011000000100110100000 &
b00011001100011000000100110100000 '
b01011000110111101100000110110001 (
#247
0#
#248
1#
b01110010011010101100101101010001 &
b01110010011010101100101101010001 '
b00011001100011000000100110100000 (
#249
0#
#250
1#
b10001011111101101101010011110001 &
b10001011111101101101010011110001 '
b01110010011010101100101101010001 (
#251
0#
#252
1#
b11111110011000011010000001000010 &
b11111110011000011010000001000010 '
b10001011111101101101010011110001 (
#253
0#
#254
1#
b10001010010110000111010100110011 &
b10001010010110000111010100110011 '
b11111110011000011010000001000010 (
#255
0#
#256
1#
b10001000101110100001010101110101 &
b10001000101110100001010101110101 '
b10001010010110000111010100110011 (
#257
0#
#258
1#
b00010011000100101000101010101000 &
b00010011000100101000101010101000 '
b10001000101110100001010101110101 (
#259
0#
#260
1#
b10011011110011001010000000011101 &
b10011011110011001010000000011101 '
b00010011000100101000101010101000 (
#261
0#
#262
1#
b10101110110111110010101011000101 &
b10101110110111110010101011000101 '
b10011011110011001010000000011101 (
#263
0#
#264
1#
b01001010101010111100101011100010 &
b01001010101010111100101011100010 '
b10101110110111110010101011000101 (
#265
0#
#266
1#
b11111001100010101111010110100111 &
b11111001100010101111010110100111 '
b01001010101010111100101011100010 (
#267
0#
#268
1#
b01000100001101101100000010001001 &
b01000100001101101100000010001001 '
b11111001100010101111010110100111 (
#269
0#
#270
1#
b00111101110000011011011000110000 &
b00111101110000011011011000110000 '
b01000100001101101100000010001001 (
#271
0#
#272
1#
b10000001111110000111011010111001 &
b10000001111110000111011010111001 '
b00111101110000011011011000110000 (
#273
0#
#274
1#
b10111111101110100010110011101001 &
b10111111101110100010110011101001 '
b10000001111110000111011010111001 (
#275
0#
#276
1#
b01000001101100101010001110100010 &
b01000001101100101010001110100010 '
b10111111101110100010110011101001 (
#277
0#
#278
1#
b00000001011011001101000010001011 &
b00000001011011001101000010001011 '
b01000001101100101010001110100010 (
#279
0#
#280
1#
b01000011000111110111010000101101 &
b01000011000111110111010000101101 '
b00000001011011001101000010001011 (
#281
0#
#282
1#
b01000100100011000100010010111000 &
b01000100100011000100010010111000 '
b01000011000111110111010000101101 (
#283
0#
#284
1#
b10000111101010111011100011100101 &
b10000111101010111011100011100101 '
b01000100100011000100010010111000 (
#285
0#
#286
1#
b11001100001101111111110110011101 &
b11001100001101111111110110011101 '
b10000111101010111011100011100101 (
#287
0#
#288
1#
b01010011111000111011011010000010 &
b01010011111000111011011010000010 '
b11001100001101111111110110011101 (
#289
0#
#290
1#
b00100000000110111011010000011111 &
b00100000000110111011010000011111 '
b01010011111000111011011010000010 (
#291
0#
#292
1#
b01110011111111110110101010100001 &
b01110011111111110110101010100001 '
b00100000000110111011010000011111 (
#293
0#
#294
1#
b10010100000110110001111011000000 &
b10010100000110110001111011000000 '
b01110011111111110110101010100001 (
#295
0#
#296
1#
b00001000000110101000100101100001 &
b00001000000110101000100101100001 '
b10010100000110110001111011000000 (
#297
0#
#298
1#
b10011100001101011010100000100001 &
b10011100001101011010100000100001 '
b00001000000110101000100101100001 (
#299
0#
#300
1#
b10100100010100000011000110000010 &
b10100100010100000011000110000010 '
b10011100001101011010100000100001 (
#301
0#
#302
1#
b01000000100001011101100110100011 &
b01000000100001011101100110100011 '
b10100100010100000011000110000010 (
#303
0#
#304
1#
b11100100110101100000101100100101 &
b11100100110101100000101100100101 '
b01000000100001011101100110100011 (
#305
0#
#306
1#
b00100101010110111110010011001000 &
b00100101010110111110010011001000 '
b11100100110101100000101100100101 (
#307
0#
#308
1#
b00001010001100011110111111101101 &
b00001010001100011110111111101101 '
b00100101010110111110010011001000 (
#309
0#
#310
1#
b00101111100011011101010010110101 &
b00101111100011011101010010110101 '
b00001010001100011110111111101101 (
#311
0#
#312
1#
b00111001101111111100010010100010 &
b00111001101111111100010010100010 '
b00101111100011011101010010110101 (
#313
0#
#314
1#
b01101001010011011001100101010111 &
b01101001010011011001100101010111 '
b00111001101111111100010010100010 (
#315
0#
#316
1#
b10100011000011010101110111111001 &
b10100011000011010101110111111001 '
b01101001010011011001100101010111 (
#317
0#
#318
1#
b00001100010110101111011101010000 &
b00001100010110101111011101010000 '
b10100011000011010101110111111001 (
#319
0#
#320
1#
b10101111011010000101010101001001 &
b10101111011010000101010101001001 '
b00001100010110101111011101010000 (
#321
0#
#322
1#
b10111011110000110100110010011001 &
b10111011110000110100110010011001 '
b10101111011010000101010101001001 (
#323
0#
#324
1#
b01101011001010111010000111100010 &
b01101011001010111010000111100010 '
b10111011110000110100110010011001 (
#325
0#
#326
1#
b00100110111011101110111001111011 &
b00100110111011101110111001111011 '
b01101011001010111010000111100010 (
#327
0#
#328
1#
b10010010000110101001000001011101 &
b10010010000110101001000001011101 '
b00100110111011101110111001111011 (
#329
0#
#330
1#
b10111001000010010111111011011000 &
b10111001000010010111111011011000 '
b10010010000110101001000001011101 (
#331
0#
#332
1#
b01001011001001000000111100110101 &
b01001011001001000000111100110101 '
b10111001000010010111111011011000 (
#333
0#
#334
1#
b00000100001011011000111000001101 &
b00000100001011011000111000001101 '
b01001011001001000000111100110101 (
#335
0#
#336
1#
b01001111010100011001110101000010 &
b01001111010100011001110101000010 '
b00000100001011011000111000001101 (
#337
0#
#338
1#
b01010011011111110010101101001111 &
b01010011011111110010101101001111 '
b01001111010100011001110101000010 (
#339
0#
#340
1#
b10100010110100001100100010010001 &
b10100010110100001100100010010001 '
b01010011011111110010101101001111 (
#341
0#
#342
1#
b11110110010011111111001111100000 &
b11110110010011111111001111100000 '
b10100010110100001100100010010001 (
#343
0#
#344
1#
b10011001001000001011110001110001 &
b10011001001000001011110001110001 '
b11110110010011111111001111100000 (
#345
0#
#346
1#
b10001111011100001011000001010001 &
b10001111011100001011000001010001 '
b10011001001000001011110001110001 (
#347
0#
#348
1#
b00101000100100010110110011000010 &
b00101000100100010110110011000010 '
b10001111011100001011000001010001 (
#349
0#
#350
1#
b10111000000000100001110100010011 &
b10111000000000100001110100010011 '
b00101000100100010110110011000010 (
#351
0#
#352
1#
b11100000100100111000100111010101 &
b11100000100100111000100111010101 '
b10111000000000100001110100010011 (
#353
0#
#354
1#
b10011000100101011010011011101000 &
b10011000100101011010011011101000 '
b11100000100100111000100111010101 (
#355
0#
#356
1#
b01111001001010010011000010111101 &
b01111001001010010011000010111101 '
b10011000100101011010011011101000 (
#357
0#
#358
1#
b00010001101111101101011110100101 &
b00010001101111101101011110100101 '
b01111001001010010011000010111101 (
#359
0#
#360
1#
b10001010111010000000100001100010 &
b10001010111010000000100001100010 '
b00010001101111101101011110100101 (
#361
0#
#362
1#
b10011100101001101110000000000111 &
b10011100101001101110000000000111 '
b10001010111010000000100001100010 (
#363
0#
#364
1#
b00100111100011101110100001101001 &
b00100111100011101110100001101001 '
b10011100101001101110000000000111 (
#365
0#
#366
1#
b11000100001101011100100001110000 &
b11000100001101011100100001110000 '
b00100111100011101110100001101001 (
#367
0#
#368
1#
b11101011110001001011000011011001 &
b11101011110001001011000011011001 '
b11000100001101011100100001110000 (
#369
0#
#370
1#
b10101111111110100111100101001001 &
b10101111111110100111100101001001 '
b11101011110001001011000011011001 (
#371
0#
#372
1#
b10011011101111110010101000100010 &
b10011011101111110010101000100010 '
b10101111111110100111100101001001 (
#373
0#
#374
1#
b01001011101110011010001101101011 &
b01001011101110011010001101101011 '
b10011011101111110010101000100010 (
#375
0#
#376
1#
b11100111011110001100110110001101 &
b11100111011110001100110110001101 '
b01001011101110011010001101101011 (
#377
0#
#378
1#
b00110011001100100111000011111000 &
b00110011001100100111000011111000 '
b11100111011110001100110110001101 (
#379
0#
#380
1#
b00011010101010110011111010000101 &
b00011010101010110011111010000101 '
b00110011001100100111000011111000 (
#381
0#
#382
1#
b01001101110111011010111101111101 &
b01001101110111011010111101111101 '
b00011010101010110011111010000101 (
#383
0#
#384
1#
b01101000100010001110111000000010 &
b01101000100010001110111000000010 '
b01001101110111011010111101111101 (
#385
0#
#386
1#
b10110110011001101001110101111111 &
b10110110011001101001110101111111 '
b01101000100010001110111000000010 (
#387
0#
#388
1#
b00011110111011111000101110000001 &
b00011110111011111000101110000001 '
b10110110011001101001110101111111 (
#389
0#
#390
1#
b11010101010101100010100100000000 &
b11010101010101100010100100000000 '
b00011110111011111000101110000001 (
#391
0#
#392
1#
b11110100010001011011010010000001 &
b11110100010001011011010010000001 '
b11010101010101100010100100000000 (
#393
0#
#394
1#
b11001001100110111101110110000001 &
b11001001100110111101110110000001 '
b11110100010001011011010010000001 (
#395
0#
#396
1#
b10111101111000011001001000000010 &
b10111101111000011001001000000010 '
b11001001100110111101110110000001 (
#397
0#
#398
1#
b10000111011111010110111110000011 &
b10000111011111010110111110000011 '
b10111101111000011001001000000010 (
#399
0#
#400
1#
b01000101010111110000000110000101 &
b01000101010111110000000110000101 '
b10000111011111010110111110000011 (
#401
0#
#402
1#
b11001100110111000111000100001000 &
b11001100110111000111000100001000 '
b01000101010111110000000110000101 (
#403
0#
#404
1#
b00010010001110110111001010001101 &
b00010010001110110111001010001101 '
b11001100110111000111000100001000 (
#405
0#
#406
1#
b11011111000101111110001110010101 &
b11011111000101111110001110010101 '
b00010010001110110111001010001101 (
#407
0#
#408
1#
b11110001010100110101011000100010 &
b11110001010100110101011000100010 '
b11011111000101111110001110010101 (
#409
0#
#410
1#
b11010000011010110011100110110111 &
b11010000011010110011100110110111 '
b11110001010100110101011000100010 (
#411
0#
#412
1#
b11000001101111101000111111011001 &
b11000001101111101000111111011001 '
b11010000011010110011100110110111 (
#413
0#
#414
1#
b10010010001010011100100110010000 &
b10010010001010011100100110010000 '
b11000001101111101000111111011001 (
#415
0#
#416
1#
b01010011111010000101100101101001 &
b01010011111010000101100101101001 '
b10010010001010011100100110010000 (
#417
0#
#418
1#
b11100110000100100010001011111001 &
b11100110000100100010001011111001 '
b01010011111010000101100101101001 (
#419
0#
#420
1#
b00111001111110100111110001100010 &
b00111001111110100111110001100010 '
b11100110000100100010001011111001 (
#421
0#
#422
1#
b00100000000011001001111101011011 &
b00100000000011001001111101011011 '
b00111001111110100111110001100010 (
#423
0#
#424
1#
b01011010000001110001101110111101 &
b01011010000001110001101110111101 '
b00100000000011001001111101011011 (
#425
0#
#426
1#
b01111010000100111011101100011000 &
b01111010000100111011101100011000 '
b01011010000001110001101110111101 (
#427
0#
#428
1#
b11010100000110101101011011010101 &
b11010100000110101101011011010101 '
b01111010000100111011101100011000 (
#429
0#
#430
1#
b01001110001011101001000111101101 &
b01001110001011101001000111101101 '
b11010100000110101101011011010101 (
#431
0#
#432
1#
b00100010010010010110100011000010 &
b00100010010010010110100011000010 '
b01001110001011101001000111101101 (
#433
0#
#434
1#
b01110000011101111111101010101111 &
b01110000011101111111101010101111 '
b00100010010010010110100011000010 (
#435
0#
#436
1#
b10010010110000010110001101110001 &
b10010010110000010110001101110001 '
b01110000011101111111101010101111 (
#437
0#
#438
1#
b00000011001110010101111000100000 &
b00000011001110010101111000100000 '
b10010010110000010110001101110001 (
#439
0#
#440
1#
b10010101111110101100000110010001 &
b10010101111110101100000110010001 '
b00000011001110010101111000100000 (
#441
0#
#442
1#
b10011001001101000001111110110001 &
b10011001001101000001111110110001 '
b10010101111110101100000110010001 (
#443
0#
#444
1#
b00101111001011101110000101000010 &
b00101111001011101110000101000010 '
b10011001001101000001111110110001 (
#445
0#
#446
1#
b11001000011000110000000011110011 &
b11001000011000110000000011110011 '
b00101111001011101110000101000010 (
#447
0#
#448
1#
b11110111100100011110001000110101 &
b11110111100100011110001000110101 '
b11001000011000110000000011110011 (
#449
0#
#450
1#
b10111111111101001110001100101000 &
b10111111111101001110001100101000 '
b11110111100100011110001000110101 (
#451
0#
#452
1#
b10110111100001101100010101011101 &
b10110111100001101100010101011101 '
b10111111111101001110001100101000 (
#453
0#
#454
1#
b01110111011110111010100010000101 &
b01110111011110111010100010000101 '
b10110111100001101100010101011101 (
#455
0#
#456
1#
b00101111000000100110110111100010 &
b00101111000000100110110111100010 '
b01110111011110111010100010000101 (
#457
0#
#458
1#
b10100110011111100001011001100111 &
b10100110011111100001011001100111 '
b00101111000000100110110111100010 (
#459
0#
#460
1#
b11010101100000001000010001001001 &
b11010101100000001000010001001001 '
b10100110011111100001011001100111 (
#461
0#
#462
1#
b01111011111111101001101010110000 &
b01111011111111101001101010110000 '
b11010101100000001000010001001001 (
#463
0#
#464
1#
b01010001011111110001111011111001 &
b01010001011111110001111011111001 '
b01111011111111101001101010110000 (
#465
0#
#466
1#
b11001101011111011011100110101001 &
b11001101011111011011100110101001 '
b01010001011111110001111011111001 (
#467
0#
#468
1#
b00011110111111001101100010100010 &
b00011110111111001101100010100010 '
b11001101011111011011100110101001 (
#469
0#
#470
1#
b11101100011110101001001001001011 &
b11101100011110101001001001001011 '
b00011110111111001101100010100010 (
#471
0#
#472
1#
b00001011011101110110101011101101 &
b00001011011101110110101011101101 '
b11101100011110101001001001001011 (
#473
0#
#474
1#
b11110111111100011111110100111000 &
b11110111111100011111110100111000 '
b00001011011101110110101011101101 (
#475
0#
#476
1#
b00000011011010010110100000100101 &
b00000011011010010110100000100101 '
b11110111111100011111110100111000 (
#477
0#
#478
1#
b11111011010110110110010101011101 &
b11111011010110110110010101011101 '
b00000011011010010110100000100101 (
#479
0#
#480
1#
b11111110110001001100110110000010 &
b11111110110001001100110110000010 '
b11111011010110110110010101011101 (
#481
0#
#482
1#
b11111010001000000011001011011111 &
b11111010001000000011001011011111 '
b11111110110001001100110110000010 (
#483
0#
#484
1#
b11111000111001010000000001100001 &
b11111000111001010000000001100001 '
b11111010001000000011001011011111 (
#485
0#
#486
1#
b11110011000001010011001101000000 &
b11110011000001010011001101000000 '
b11111000111001010000000001100001 (
#487
0#
#488
1#
b11101011111010100011001110100001 &
b11101011111010100011001110100001 '
b11110011000001010011001101000000 (
#489
0#
#490
1#
b11011110111011110110011011100001 &
b11011110111011110110011011100001 '
b11101011111010100011001110100001 (
#491
0#
#492
1#
b11001010110110011001101010000010 &
b11001010110110011001101010000010 '
b11011110111011110110011011100001 (
#493
0#
#494
1#
b10101001110010010000000101100011 &
b10101001110010010000000101100011 '
b11001010110110011001101010000010 (
#495
0#
#496
1#
b01110100101000101001101111100101 &
b01110100101000101001101111100101 '
b10101001110010010000000101100011 (
#497
0#
#498
1#
b00011110011010111001110101001000 &
b00011110011010111001110101001000 '
b01110100101000101001101111100101 (
#499
0#
#500
1#
b10010011000011100011100100101101 &
b10010011000011100011100100101101 '
b00011110011010111001110101001000 (
#501
0#
#502
1#
b10110001011110011101011001110101 &
b10110001011110011101011001110101 '
b10010011000011100011100100101101 (
#503
0#
#504
1#
b01000100100010000000111110100010 &
b01000100100010000000111110100010 '
b10110001011110011101011001110101 (
#505
0#
#506
1#
b11110110000000011110011000010111 &
b11110110000000011110011000010111 '
b01000100100010000000111110100010 (
#507
0#
